dz_mongodb/__init__.py
dz_mongodb/config_utils.py
dz_mongodb/datetime_utils.py
dz_mongodb/db_utils.py
dz_mongodb/errors.py
dz_mongodb/stream_utils.py
dz_mongodb/sync_strategies/change_streams.py
dz_mongodb/sync_strategies/common.py
dz_mongodb/sync_strategies/full_table.py
dz_mongodb/sync_strategies/incremental.py
sh_mongodb/__init__.py
sh_mongodb/config_utils.py
sh_mongodb/datetime_utils.py
sh_mongodb/db_utils.py
sh_mongodb/errors.py
sh_mongodb/stream_utils.py
sh_mongodb/sync_strategies/change_streams.py
sh_mongodb/sync_strategies/common.py
sh_mongodb/sync_strategies/full_table.py
sh_mongodb/sync_strategies/incremental.py
sh_mongodb-1.0.1.dist-info/LICENSE
sh_mongodb-1.0.1.dist-info/METADATA
sh_mongodb-1.0.1.dist-info/WHEEL
sh_mongodb-1.0.1.dist-info/entry_points.txt
sh_mongodb-1.0.1.dist-info/top_level.txt
sh_mongodb-1.0.1.dist-info/RECORD
