Metadata-Version: 2.1
Name: sh-mongodb
Version: 1.0.1
Summary: Singer.io tap for extracting data from MongoDB - Datazip compatible
Home-page: https://github.com/datazip/dz-mongodb
Author: Wise
License: UNKNOWN
Platform: UNKNOWN
Classifier: Programming Language :: Python :: 3 :: Only
Classifier: Programming Language :: Python :: 3.6
Classifier: Programming Language :: Python :: 3.7
Classifier: Programming Language :: Python :: 3.8
License-File: LICENSE
Requires-Dist: pipelinewise-singer-python (==2.0.1)
Requires-Dist: pymongo (==4.4.0)
Requires-Dist: tzlocal (==4.0.1)
Requires-Dist: terminaltables (==3.1.10)
Requires-Dist: dnspython (==2.3.0)
Provides-Extra: dev
Requires-Dist: pylint (==2.12) ; extra == 'dev'
Requires-Dist: ipdb (==0.13.*) ; extra == 'dev'
Provides-Extra: test
Requires-Dist: pytest (==6.2.5) ; extra == 'test'
Requires-Dist: pytest-cov (==3.0.0) ; extra == 'test'
